MANIFEST.in
setup.cfg
setup.py
django_usage/__init__.py
django_usage/admin.py
django_usage/middleware.py
django_usage/models.py
django_usage/reports.py
django_usage/settings.py
django_usage/urls.py
django_usage/views.py
django_usage.egg-info/PKG-INFO
django_usage.egg-info/SOURCES.txt
django_usage.egg-info/dependency_links.txt
django_usage.egg-info/requires.txt
django_usage.egg-info/top_level.txt
django_usage/migrations/__init__.py
django_usage/migrations/__pycache__/__init__.cpython-35.pyc
django_usage/templates/django_usage/chart.html
django_usage/templates/django_usage/charts_map.html
tests/__init__.py