Metadata-Version: 1.1
Name: django-usage
Version: 0.0.1a5
Summary: Django usage reports
Home-page: https://github.com/regisec/django-usage/
Author: Régis Eduardo Crestani
Author-email: regis.crestani@gmail.com
License: BSD
Platform: UNKNOWN
Classifier: Development Status :: 3 - Alpha
Classifier: Intended Audience :: Developers
Classifier: Framework :: Django
Classifier: Topic :: Software Development
Classifier: License :: OSI Approved :: BSD License
Classifier: Programming Language :: Python
Classifier: Programming Language :: Python :: 2
Classifier: Programming Language :: Python :: 3
